ecg_marker/__init__.py
ecg_marker/__main__.py
ecg_marker/ecg_marker.py
ecg_marker-2.0.0.dist-info/licenses/LICENSE
ecg_marker-2.0.0.dist-info/METADATA
ecg_marker-2.0.0.dist-info/WHEEL
ecg_marker-2.0.0.dist-info/top_level.txt
ecg_marker-2.0.0.dist-info/RECORD
