Metadata-Version: 2.4
Name: ecg_marker
Version: 2.0.0
Summary: This program allows the interactive visualization and annotation of ECG tracings from input files (either raw data or previously annotated)
Author-email: Thais Soares <thaissoares150102@gmail.com>
License-Expression: MIT
Project-URL: Homepage, https://github.com/SoaThais/ECG_MARKER.git
Classifier: Programming Language :: Python :: 3
Classifier: Operating System :: OS Independent
Requires-Python: >=3.9
License-File: LICENSE
Requires-Dist: numpy
Requires-Dist: matplotlib
Requires-Dist: neurokit2
Requires-Dist: pillow
Requires-Dist: scipy
Requires-Dist: requests
Dynamic: license-file
